Metadata-Version: 2.1
Name: FutureLog
Version: 0.1.1
Summary: Consume logs by block in async application
Home-page: https://github.com/kpetremann/futurelog
Author: Kevin Petremann
Author-email: kpetrem@gmail.com
License: MIT
Project-URL: Source, https://github.com/kpetremann/futurelog
Platform: UNKNOWN
Classifier: Development Status :: 3 - Alpha
Classifier: Intended Audience :: Developers
Classifier: License :: OSI Approved :: MIT License
Classifier: Natural Language :: English
Classifier: Operating System :: OS Independent
Classifier: Programming Language :: Python
Classifier: Topic :: System :: Logging
Requires-Python: >=3.6
